composabl_api/common.cpython-310-darwin.so
composabl_api/__init__.cpython-310-darwin.so
composabl_api/nocode/__init__.cpython-310-darwin.so
composabl_api/nocode/main.cpython-310-darwin.so
composabl_api/util/token.cpython-310-darwin.so
composabl_api/util/logger.cpython-310-darwin.so
composabl_api/util/__init__.cpython-310-darwin.so
composabl_api/util/singleton.cpython-310-darwin.so
composabl_api/controller/job_status_enum.cpython-310-darwin.so
composabl_api/controller/service.cpython-310-darwin.so
composabl_api/controller/__init__.cpython-310-darwin.so
composabl_api/controller/main.cpython-310-darwin.so
composabl_api-0.19.1.dist-info/RECORD
composabl_api-0.19.1.dist-info/WHEEL
composabl_api-0.19.1.dist-info/top_level.txt
composabl_api-0.19.1.dist-info/METADATA
